ash_cli/__init__.py
ash_cli/ash.py
ash_cli-2.0.0.dist-info/METADATA
ash_cli-2.0.0.dist-info/WHEEL
ash_cli-2.0.0.dist-info/entry_points.txt
ash_cli-2.0.0.dist-info/top_level.txt
ash_cli-2.0.0.dist-info/RECORD
